optional/__init__.py
optional/_version.py
PyOptionalLib-0.0.1rc0.dist-info/LICENSE
PyOptionalLib-0.0.1rc0.dist-info/METADATA
PyOptionalLib-0.0.1rc0.dist-info/WHEEL
PyOptionalLib-0.0.1rc0.dist-info/top_level.txt
PyOptionalLib-0.0.1rc0.dist-info/RECORD
