Metadata-Version: 2.2
Name: PyOptionalLib
Version: 0.0.1rc0
Summary: An Implementation of the Optional Object for Python
Author-email: alexandre399 <alexandre399.pypi@gmail.com>
Maintainer-email: alexandre399 <alexandre399.pypi@gmail.com>
License:                     GNU GENERAL PUBLIC LICENSE
Project-URL: Changelog, https://github.com/alexandre399/PyOptionalLib/blob/main/CHANGELOG.md
Project-URL: Documentation, https://github.com/alexandre399/PyOptionalLib/blob/main/README.md
Project-URL: Homepage, https://github.com/alexandre399/PyOptionalLib/tree/main
Project-URL: Issues, https://github.com/alexandre399/PyOptionalLib/issues
Project-URL: Repository, https://github.com/alexandre399/PyOptionalLib.git
Keywords: Optional
Classifier: Development Status :: 4 - Beta
Classifier: Intended Audience :: Developers
Classifier: Programming Language :: Python :: 3
Classifier: Programming Language :: Python :: 3.10
Classifier: Programming Language :: Python :: 3.11
Classifier: Programming Language :: Python :: 3.12
Requires-Python: >=3.10
License-File: LICENSE
